pcase/__init__.py
pcase/caseCreate.py
pcase/conf.py
pcase/excelOperation.py
pcase/zhengjiao.py
pcase-1.0.1.dist-info/LICENSE
pcase-1.0.1.dist-info/METADATA
pcase-1.0.1.dist-info/WHEEL
pcase-1.0.1.dist-info/top_level.txt
pcase-1.0.1.dist-info/RECORD
