Metadata-Version: 2.1
Name: pcase
Version: 1.0.1
Summary: A tool for generate test csse
Author-email: Light <278391313@qq.com>
Project-URL: Homepage, https://github.com/MRstrongerCL/pcase/
Project-URL: Bug Tracker, https://github.com/MRstrongerCL/pcase/issues
Classifier: Programming Language :: Python :: 3
Classifier: License :: OSI Approved :: MIT License
Classifier: Operating System :: OS Independent
Requires-Python: >=3.9
License-File: LICENSE
Requires-Dist: pyDOE2 (>=1.3.0)
Requires-Dist: xlrd (>=2.0.1)
Requires-Dist: xlwt (>=1.3.0)
